aunly_captcha_solver-0.1.3.dist-info/METADATA
aunly_captcha_solver-0.1.3.dist-info/WHEEL
aunly_captcha_solver/__init__.py
aunly_captcha_solver-0.1.3.dist-info/RECORD
