Metadata-Version: 2.1
Name: aunly-captcha-solver
Version: 0.1.3
Summary: 适用于 B 站手机网页版的点选验证码识别
Author-Email: djkcyl <cyl@cyllive.cn>
License: AGPLv3
Requires-Python: >=3.8
Requires-Dist: playwright>=1.35.0
Requires-Dist: httpx>=0.24.1
Requires-Dist: loguru>=0.7.0
Requires-Dist: pydantic<=2.0,>=1.10
